asynkit-0.17.6.dist-info/RECORD
asynkit-0.17.6.dist-info/WHEEL
asynkit-0.17.6.dist-info/top_level.txt
asynkit-0.17.6.dist-info/METADATA
asynkit-0.17.6.dist-info/licenses/LICENSE
asynkit/compat.py
asynkit/monitor.py
asynkit/tools.py
asynkit/__init__.py
asynkit/coroutine.py
asynkit/py.typed
asynkit/scheduling.py
asynkit/_cext.cpython-314-darwin.so
asynkit/experimental/anyio.py
asynkit/experimental/interrupt.py
asynkit/experimental/__init__.py
asynkit/experimental/priority.py
asynkit/loop/__init__.py
asynkit/loop/eventloop.py
asynkit/loop/types.py
asynkit/loop/extensions.py
asynkit/loop/default.py
asynkit/loop/schedulingloop.py
