Metadata-Version: 2.4
Name: asynkit
Version: 0.17.6
Summary: A toolkit for Python coroutines
Author-email: Kristján Valur Jónsson <sweskman@gmail.com>
License: MIT
Project-URL: Repository, https://github.com/kristjanvalur/py-asynkit
Keywords: asyncio,eventloop
Classifier: Development Status :: 3 - Alpha
Classifier: Topic :: Software Development :: Libraries :: Python Modules
Classifier: Framework :: AsyncIO
Classifier: License :: OSI Approved :: MIT License
Classifier: Programming Language :: Python :: 3
Classifier: Programming Language :: Python :: 3.10
Classifier: Programming Language :: Python :: 3.11
Classifier: Programming Language :: Python :: 3.12
Classifier: Programming Language :: Python :: 3.13
Classifier: Programming Language :: Python :: 3.14
Classifier: Programming Language :: Python :: Implementation :: CPython
Classifier: Programming Language :: Python :: Implementation :: PyPy
Requires-Python: >=3.10
License-File: LICENSE
Requires-Dist: typing-extensions>=4.4.0
Provides-Extra: trio
Requires-Dist: trio>=0.31.0; extra == "trio"
Dynamic: license-file
